kloudkit/testshed/__init__.py
kloudkit/testshed/py.typed
kloudkit/testshed/core/__init__.py
kloudkit/testshed/core/bootstrap.py
kloudkit/testshed/core/state.py
kloudkit/testshed/core/wrapper.py
kloudkit/testshed/docker/__init__.py
kloudkit/testshed/docker/container.py
kloudkit/testshed/docker/container_config.py
kloudkit/testshed/docker/decorators.py
kloudkit/testshed/docker/factory.py
kloudkit/testshed/docker/probes/http_probe.py
kloudkit/testshed/docker/probes/readiness_check.py
kloudkit/testshed/docker/runtime/cleanup.py
kloudkit/testshed/docker/runtime/error_handler.py
kloudkit/testshed/docker/runtime/file_system.py
kloudkit/testshed/docker/runtime/shell.py
kloudkit/testshed/docker/volumes/base_volume.py
kloudkit/testshed/docker/volumes/inline_volume.py
kloudkit/testshed/docker/volumes/remote_volume.py
kloudkit/testshed/docker/volumes/volume_manager.py
kloudkit/testshed/fixtures/docker.py
kloudkit/testshed/fixtures/generic.py
kloudkit/testshed/fixtures/playwright.py
kloudkit/testshed/fixtures/shed.py
kloudkit/testshed/playwright/__init__.py
kloudkit/testshed/playwright/factory.py
kloudkit/testshed/plugin/__init__.py
kloudkit/testshed/plugin/addoptions.py
kloudkit/testshed/plugin/configure.py
kloudkit/testshed/plugin/fixtures.py
kloudkit/testshed/plugin/markers.py
kloudkit/testshed/plugin/presenter.py
kloudkit/testshed/plugin/session.py
kloudkit/testshed/plugin/validation.py
kloudkit/testshed/utils/http.py
kloudkit/testshed/utils/network.py
kloudkit/testshed/utils/version.py
testshed-0.0.3.dist-info/licenses/LICENSE
testshed-0.0.3.dist-info/METADATA
testshed-0.0.3.dist-info/WHEEL
testshed-0.0.3.dist-info/entry_points.txt
testshed-0.0.3.dist-info/top_level.txt
testshed-0.0.3.dist-info/RECORD
