Metadata-Version: 2.4
Name: testshed
Version: 0.0.3
Summary: 🛠️ PyTest's tool shed: Docker up, Playwright on, cleanup done
Author-email: Dov Benyomin Sohacheski <b@kloud.email>
License: MIT
Project-URL: Homepage, https://github.com/kloudkit/testshed
Project-URL: Bug Tracker, https://github.com/kloudkit/testshed/issues
Project-URL: Source Code, https://github.com/kloudkit/testshed
Keywords: pytest,docker,fixtures,playwright,testing
Classifier: Framework :: Pytest
Classifier: License :: OSI Approved :: MIT License
Classifier: Operating System :: OS Independent
Classifier: Programming Language :: Python :: 3.11
Classifier: Programming Language :: Python :: 3.12
Classifier: Typing :: Typed
Requires-Python: >=3.11
License-File: LICENSE
Requires-Dist: playwright<2.0.0,>=1.54.0
Requires-Dist: pytest<9.0.0,>=8.4.1
Requires-Dist: python-on-whales<1.0.0,>=0.78.0
Requires-Dist: PyYAML<7.0.0,>=6.0.2
Requires-Dist: requests<3.0.0,>=2.32.4
Provides-Extra: dev
Requires-Dist: pre-commit>=4.2.0; extra == "dev"
Requires-Dist: ruff>=0.12.0; extra == "dev"
Requires-Dist: coverage>=7.10.6; extra == "dev"
Requires-Dist: pytest-cov>=7.0.0; extra == "dev"
Dynamic: license-file
